vocore_screen/__init__.py
vocore_screen/example.py
vocore_screen/font.py
vocore_screen/image.py
vocore_screen/screen.py
vocore_screen-0.1.1.dist-info/METADATA
vocore_screen-0.1.1.dist-info/WHEEL
vocore_screen-0.1.1.dist-info/entry_points.txt
vocore_screen-0.1.1.dist-info/license_files/LICENSE
vocore_screen-0.1.1.dist-info/RECORD
