Metadata-Version: 2.1
Name: vocore-screen
Version: 0.1.1
Summary: Library to control the Vocore Touchscreen
Project-URL: Bug Tracker, https://github.com/Orangensaft/vocore-screen-py/issues
Project-URL: Homepage, https://github.com/Orangensaft/vocore-screen-py
Author-email: Nicolas Meisberger <vocore-screen@bitshift.wtf>
Classifier: License :: OSI Approved :: GNU General Public License v3 (GPLv3)
Classifier: Operating System :: OS Independent
Classifier: Programming Language :: Python :: 3
Classifier: Topic :: System :: Hardware :: Universal Serial Bus (USB) :: Human Interface Device (HID)
Requires-Python: >=3.7
Requires-Dist: pyusb
